deepclient/__init__.py
deepclient/deep_client.py
deepclient/deep_client_options.py
deepclient/query.py
deepclient/gql_operations/__init__.py
deepclient/gql_operations/mutation.py
deepclient/gql_operations/serial.py
tests/__init__.py
tests/test_deep_client.py
deepclient-1.0.2.dist-info/METADATA
deepclient-1.0.2.dist-info/WHEEL
deepclient-1.0.2.dist-info/top_level.txt
deepclient-1.0.2.dist-info/RECORD
