Metadata-Version: 2.1
Name: deepclient
Version: 1.0.2
Summary: Deep Client - a way to connect your favorite language with Deep
Home-page: https://github.com/deep-foundation/deepclient
License: Unlicense
Classifier: Development Status :: 3 - Alpha
Classifier: License :: OSI Approved :: The Unlicense (Unlicense)
Classifier: Programming Language :: Python
Classifier: Programming Language :: Python :: 3
Classifier: Programming Language :: Python :: 3.6
Classifier: Programming Language :: Python :: 3.7
Classifier: Programming Language :: Python :: 3.8
Classifier: Programming Language :: Python :: 3.9
